portchoice/__init__.py
portchoice/design.py
portchoice/generate.py
portchoice/models.py
portchoice/utils.py
portchoice-0.4.1.dist-info/WHEEL
portchoice-0.4.1.dist-info/METADATA
portchoice-0.4.1.dist-info/RECORD
