Metadata-Version: 2.1
Name: portchoice
Version: 0.4.1
Summary: Modules to design and estimate portfolio choice models
Author: Jose Ignacio Hernandez
Author-email: j.i.hernandez@tudelft.nl
Requires-Python: >=3.8
Classifier: Programming Language :: Python :: 3
Classifier: Programming Language :: Python :: 3.10
Classifier: Programming Language :: Python :: 3.8
Classifier: Programming Language :: Python :: 3.9
Requires-Dist: numdifftools (>=0.9.40,<0.10.0)
Requires-Dist: pandas (>=1.4.2,<2.0.0)
Requires-Dist: pyDOE2 (>=1.3.0,<2.0.0)
